BloomEffect/__init__.pxd
BloomEffect/__init__.py
BloomEffect/bloom.c
BloomEffect/bloom.cp36-win_amd64.pyd
BloomEffect/bloom.pxd
BloomEffect/bloom.pyx
BloomEffect/deprecated.pyx
BloomEffect/example.py
BloomEffect/setup_bloom.py
BloomEffect/Assets/Aliens.jpg
BloomEffect/Assets/I1.png
BloomEffect/Assets/background_checker.png
BloomEffect/Assets/bloom_bpf_values.png
BloomEffect/Assets/bloom_smooth_values.png
BloomEffect/Assets/color_mask_circle.png
BloomEffect/Assets/control.png
BloomEffect/Assets/i2.png
BloomEffect/Assets/i2_bloom.png
BloomEffect/Assets/i3.png
BloomEffect/Assets/i3_bloom.png
BloomEffect/Assets/text_bloom.png
BloomEffect/__pycache__/__init__.cpython-36.pyc
BloomEffect/__pycache__/__init__.cpython-38.pyc
BloomEffect/tests/profiling.py
BloomEffect/tests/test_bloom.py
BloomEffect-1.0.2.data/data/lib/site-packages/BloomEffect/LICENSE
BloomEffect-1.0.2.data/data/lib/site-packages/BloomEffect/MANIFEST.in
BloomEffect-1.0.2.data/data/lib/site-packages/BloomEffect/README.md
BloomEffect-1.0.2.data/data/lib/site-packages/BloomEffect/__init__.pxd
BloomEffect-1.0.2.data/data/lib/site-packages/BloomEffect/__init__.py
BloomEffect-1.0.2.data/data/lib/site-packages/BloomEffect/bloom.pxd
BloomEffect-1.0.2.data/data/lib/site-packages/BloomEffect/bloom.pyx
BloomEffect-1.0.2.data/data/lib/site-packages/BloomEffect/deprecated.pyx
BloomEffect-1.0.2.data/data/lib/site-packages/BloomEffect/example.py
BloomEffect-1.0.2.data/data/lib/site-packages/BloomEffect/pyproject.toml
BloomEffect-1.0.2.data/data/lib/site-packages/BloomEffect/requirements.txt
BloomEffect-1.0.2.data/data/lib/site-packages/BloomEffect/setup_bloom.py
BloomEffect-1.0.2.data/data/lib/site-packages/BloomEffect/Assets/Aliens.jpg
BloomEffect-1.0.2.data/data/lib/site-packages/BloomEffect/Assets/I1.png
BloomEffect-1.0.2.data/data/lib/site-packages/BloomEffect/Assets/background_checker.png
BloomEffect-1.0.2.data/data/lib/site-packages/BloomEffect/Assets/bloom_bpf_values.png
BloomEffect-1.0.2.dist-info/LICENSE
BloomEffect-1.0.2.dist-info/METADATA
BloomEffect-1.0.2.dist-info/WHEEL
BloomEffect-1.0.2.dist-info/top_level.txt
BloomEffect-1.0.2.dist-info/RECORD
